repoai/__init__.py
repoai/main.py
repoai/components/__init__.py
repoai/components/components_base.py
repoai/components/module_loader.py
repoai/components/interfaces/__init__.py
repoai/components/interfaces/project_generation_interface.py
repoai/components/interfaces/project_modification_interface.py
repoai/components/tasks/__init__.py
repoai/components/tasks/file_content_generation_task.py
repoai/components/tasks/file_edit_task.py
repoai/components/tasks/project_description_chat_task.py
repoai/components/tasks/project_modification_task.py
repoai/components/tasks/project_structure_chat_task.py
repoai/components/tasks/structure_to_paths_task.py
repoai/components/workflows/__init__.py
repoai/components/workflows/project_generation_workflow.py
repoai/components/workflows/project_modification_workflow.py
repoai/core/__init__.py
repoai/core/config_manager.py
repoai/core/file_manager.py
repoai/core/plugin_manager.py
repoai/core/project_manager.py
repoai/core/prompt_manager.py
repoai/defaults/__init__.py
repoai/defaults/default_config.py
repoai/defaults/default_interface_prompts.py
repoai/defaults/default_llm_prompts.py
repoai/services/__init__.py
repoai/services/docker_service.py
repoai/services/git_service.py
repoai/services/llm_service.py
repoai/services/markdown_service.py
repoai/services/progress_service.py
repoai/templates/gitignore.j2
repoai/templates/repoaiignore.j2
repoai/utils/__init__.py
repoai/utils/common_utils.py
repoai/utils/ignore_patterns.py
repoai/utils/logger.py
repoai/utils/markdown_generator.py
repoai/utils/response_wrapper.py
repoai/utils/token_counter.py
repoai/utils/treenode.py
repoai-0.0.4.dist-info/LICENSE
repoai-0.0.4.dist-info/METADATA
repoai-0.0.4.dist-info/WHEEL
repoai-0.0.4.dist-info/entry_points.txt
repoai-0.0.4.dist-info/top_level.txt
repoai-0.0.4.dist-info/RECORD
