Metadata-Version: 2.1
Name: repoai
Version: 0.0.4
Summary: AI-assisted repository content creation and editing
Author-email: Carlos Gaete-Morales <cdgaete@gmail.com>
License: Apache License
Classifier: Programming Language :: Python :: 3
Classifier: License :: OSI Approved :: MIT License
Classifier: Operating System :: OS Independent
Requires-Python: >=3.9
License-File: LICENSE
Requires-Dist: gitpython
Requires-Dist: appdirs
Requires-Dist: chardet
Requires-Dist: docker
Requires-Dist: litellm
Requires-Dist: rich
Requires-Dist: Pillow
Requires-Dist: pyyaml
Requires-Dist: jinja2
Provides-Extra: dev
Requires-Dist: pytest; extra == "dev"
Requires-Dist: flake8; extra == "dev"
Requires-Dist: mypy; extra == "dev"
Requires-Dist: black; extra == "dev"
